pytest_httpbin/__init__.py
pytest_httpbin/certs.py
pytest_httpbin/plugin.py
pytest_httpbin/serve.py
pytest_httpbin/version.py
pytest_httpbin/certs/cacert.pem
pytest_httpbin/certs/cert.pem
pytest_httpbin/certs/key.pem
pytest_httpbin-2.0.0.dist-info/METADATA
pytest_httpbin-2.0.0.dist-info/WHEEL
pytest_httpbin-2.0.0.dist-info/entry_points.txt
pytest_httpbin-2.0.0.dist-info/top_level.txt
pytest_httpbin-2.0.0.dist-info/RECORD
