Metadata-Version: 2.1
Name: pytest-httpbin
Version: 2.0.0
Summary: Easily test your HTTP library against a local copy of httpbin
Home-page: https://github.com/kevin1024/pytest-httpbin
Author: Kevin McCarthy
Author-email: me@kevinmccarthy.org
License: MIT
Keywords: pytest-httpbin testing pytest httpbin
Classifier: Development Status :: 5 - Production/Stable
Classifier: Intended Audience :: Developers
Classifier: Topic :: Software Development :: Testing
Classifier: Topic :: Software Development :: Libraries
Classifier: License :: OSI Approved :: MIT License
Classifier: Programming Language :: Python :: 3
Classifier: Programming Language :: Python :: 3 :: Only
Classifier: Programming Language :: Python :: 3.7
Classifier: Programming Language :: Python :: 3.8
Classifier: Programming Language :: Python :: 3.9
Classifier: Programming Language :: Python :: 3.10
Classifier: Programming Language :: Python :: 3.11
Requires-Python: >=3.7
Requires-Dist: httpbin
Provides-Extra: test
Requires-Dist: requests ; extra == 'test'
Requires-Dist: pytest ; extra == 'test'
Requires-Dist: werkzeug (<2.1.0) ; extra == 'test'
